README.md
setup.py
berttextclassification/BertModel.py
berttextclassification/DataLawlaw.py
berttextclassification/__init__.py
berttextclassification/acc_and_f1.py
berttextclassification/bert_lawlaw.py
berttextclassification/evaluate.py
berttextclassification/predict.py
berttextclassification/train.py
berttextclassification.egg-info/PKG-INFO
berttextclassification.egg-info/SOURCES.txt
berttextclassification.egg-info/dependency_links.txt
berttextclassification.egg-info/entry_points.txt
berttextclassification.egg-info/top_level.txt