Metadata-Version: 2.1
Name: berttextclassification
Version: 0.1.2
Summary: 训练/使用Bert分类模型
Home-page: https://pypi.org/user/May.xiaoya.zhang/
Author: may.xiaoya.zhang
Author-email: may.xiaoya.zhang@gmail.com
License: UNKNOWN
Platform: UNKNOWN
